odoo/addons/product_weight_through_uom/README.rst
odoo/addons/product_weight_through_uom/__init__.py
odoo/addons/product_weight_through_uom/__manifest__.py
odoo/addons/product_weight_through_uom/hooks.py
odoo/addons/product_weight_through_uom/i18n/es.po
odoo/addons/product_weight_through_uom/i18n/product_weight_through_uom.pot
odoo/addons/product_weight_through_uom/models/__init__.py
odoo/addons/product_weight_through_uom/models/product.py
odoo/addons/product_weight_through_uom/models/product_template.py
odoo/addons/product_weight_through_uom/readme/CONFIGURE.rst
odoo/addons/product_weight_through_uom/readme/CONTRIBUTORS.rst
odoo/addons/product_weight_through_uom/readme/DESCRIPTION.rst
odoo/addons/product_weight_through_uom/readme/INSTALL.rst
odoo/addons/product_weight_through_uom/readme/ROADMAP.rst
odoo/addons/product_weight_through_uom/readme/USAGE.rst
odoo/addons/product_weight_through_uom/static/description/icon.png
odoo/addons/product_weight_through_uom/static/description/index.html
odoo/addons/product_weight_through_uom/tests/__init__.py
odoo/addons/product_weight_through_uom/tests/test_product_weight_through_uom.py
odoo/addons/product_weight_through_uom/views/product_views.xml
odoo11_addon_product_weight_through_uom-11.0.1.0.0.99.dev7.dist-info/METADATA
odoo11_addon_product_weight_through_uom-11.0.1.0.0.99.dev7.dist-info/WHEEL
odoo11_addon_product_weight_through_uom-11.0.1.0.0.99.dev7.dist-info/top_level.txt
odoo11_addon_product_weight_through_uom-11.0.1.0.0.99.dev7.dist-info/RECORD
